[{"Province_State":"Alabama","Country_Region":"US","Last_Update":"2020-09-15 03:30:30","Lat":32.3182,"Long_":-86.9023,"Confirmed":139459,"Deaths":2355,"Recovered":54223.0,"Active":82881.0,"FIPS":1.0,"Incident_Rate":2844.2532761868,"People_Tested":1027551.0,"Mortality_Rate":1.6886683541,"UID":84000001,"ISO3":"USA","Testing_Rate":20956.806647108},{"Province_State":"Alaska","Country_Region":"US","Last_Update":"2020-09-15 03:30:30","Lat":61.3707,"Long_":-152.4044,"Confirmed":6343,"Deaths":44,"Recovered":2377.0,"Active":3922.0,"FIPS":2.0,"Incident_Rate":867.0690114757,"People_Tested":403413.0,"Mortality_Rate":0.6936780703,"UID":84000002,"ISO3":"USA","Testing_Rate":55145.3430752722},{"Province_State":"American Samoa","Country_Region":"US","Last_Update":"2020-09-15 03:30:30","Lat":-14.271,"Long_":-170.132,"Confirmed":0,"Deaths":0,"Recovered":null,"Active":0.0,"FIPS":60.0,"Incident_Rate":0.0,"People_Tested":1571.0,"Mortality_Rate":0.0,"UID":16,"ISO3":"ASM","Testing_Rate":2823.4575223307},{"Province_State":"Arizona","Country_Region":"US","Last_Update":"2020-09-15 03:30:30","Lat":33.7298,"Long_":-111.4312,"Confirmed":208725,"Deaths":5322,"Recovered":32975.0,"Active":170428.0,"FIPS":4.0,"Incident_Rate":2867.6070246995,"People_Tested":1300664.0,"Mortality_Rate":2.5497664391,"UID":84000004,"ISO3":"USA","Testing_Rate":17869.4129748416},{"Province_State":"Arkansas","Country_Region":"US","Last_Update":"2020-09-15 03:30:30","Lat":34.9697,"Long_":-92.3731,"Confirmed":70627,"Deaths":992,"Recovered":62740.0,"Active":6895.0,"FIPS":5.0,"Incident_Rate":2340.3441707944,"People_Tested":828267.0,"Mortality_Rate":1.4045619947,"UID":84000005,"ISO3":"USA","Testing_Rate":27446.0170375545},{"Province_State":"California","Country_Region":"US","Last_Update":"2020-09-15 03:30:30","Lat":36.1162,"Long_":-119.6816,"Confirmed":765134,"Deaths":14439,"Recovered":null,"Active":750695.0,"FIPS":6.0,"Incident_Rate":1936.4488806413,"People_Tested":12806189.0,"Mortality_Rate":1.887120426,"UID":84000006,"ISO3":"USA","Testing_Rate":32410.7023793625},{"Province_State":"Colorado","Country_Region":"US","Last_Update":"2020-09-15 03:30:30","Lat":39.0598,"Long_":-105.3111,"Confirmed":61667,"Deaths":1990,"Recovered":6162.0,"Active":53515.0,"FIPS":8.0,"Incident_Rate":1070.8426293548,"People_Tested":1124181.0,"Mortality_Rate":3.2270095837,"UID":84000008,"ISO3":"USA","Testing_Rate":19521.3150941457},{"Province_State":"Connecticut","Country_Region":"US","Last_Update":"2020-09-15 03:30:30","Lat":41.5978,"Long_":-72.7554,"Confirmed":54895,"Deaths":4485,"Recovered":9142.0,"Active":41268.0,"FIPS":9.0,"Incident_Rate":1539.7077430232,"People_Tested":1379988.0,"Mortality_Rate":8.1701430003,"UID":84000009,"ISO3":"USA","Testing_Rate":38706.2247723676},{"Province_State":"Delaware","Country_Region":"US","Last_Update":"2020-09-15 03:30:30","Lat":39.3185,"Long_":-75.5071,"Confirmed":18937,"Deaths":617,"Recovered":10091.0,"Active":8229.0,"FIPS":10.0,"Incident_Rate":1944.7217190202,"People_Tested":262504.0,"Mortality_Rate":3.2581718329,"UID":84000010,"ISO3":"USA","Testing_Rate":26957.6611992228},{"Province_State":"District of Columbia","Country_Region":"US","Last_Update":"2020-09-15 03:30:30","Lat":38.8974,"Long_":-77.0268,"Confirmed":14622,"Deaths":616,"Recovered":11592.0,"Active":2414.0,"FIPS":11.0,"Incident_Rate":2071.8414053722,"People_Tested":332148.0,"Mortality_Rate":4.2128299822,"UID":84000011,"ISO3":"USA","Testing_Rate":47063.1910211704},{"Province_State":"Florida","Country_Region":"US","Last_Update":"2020-09-15 03:30:30","Lat":27.7663,"Long_":-81.6868,"Confirmed":665730,"Deaths":12642,"Recovered":null,"Active":653088.0,"FIPS":12.0,"Incident_Rate":3099.6282336449,"People_Tested":4941008.0,"Mortality_Rate":1.8989680501,"UID":84000012,"ISO3":"USA","Testing_Rate":23005.2542313932},{"Province_State":"Georgia","Country_Region":"US","Last_Update":"2020-09-15 03:30:30","Lat":33.0406,"Long_":-83.6431,"Confirmed":295337,"Deaths":6353,"Recovered":null,"Active":288984.0,"FIPS":13.0,"Incident_Rate":2781.6260122631,"People_Tested":2615247.0,"Mortality_Rate":2.1511019615,"UID":84000013,"ISO3":"USA","Testing_Rate":24631.6549693838},{"Province_State":"Guam","Country_Region":"US","Last_Update":"2020-09-15 03:30:30","Lat":13.4443,"Long_":144.7937,"Confirmed":1927,"Deaths":26,"Recovered":1274.0,"Active":627.0,"FIPS":66.0,"Incident_Rate":1173.3615865651,"People_Tested":43894.0,"Mortality_Rate":1.349247535,"UID":316,"ISO3":"GUM","Testing_Rate":26727.3136900304},{"Province_State":"Hawaii","Country_Region":"US","Last_Update":"2020-09-15 03:30:30","Lat":21.0943,"Long_":-157.4983,"Confirmed":10779,"Deaths":99,"Recovered":3565.0,"Active":7115.0,"FIPS":15.0,"Incident_Rate":761.2976314243,"People_Tested":259531.0,"Mortality_Rate":0.9184525466,"UID":84000015,"ISO3":"USA","Testing_Rate":18330.1174117434},{"Province_State":"Idaho","Country_Region":"US","Last_Update":"2020-09-15 03:30:30","Lat":44.2405,"Long_":-114.4788,"Confirmed":35532,"Deaths":419,"Recovered":18619.0,"Active":16913.0,"FIPS":16.0,"Incident_Rate":1974.1307674875,"People_Tested":278613.0,"Mortality_Rate":1.1763371978,"UID":84000016,"ISO3":"USA","Testing_Rate":15590.5353190846},{"Province_State":"Illinois","Country_Region":"US","Last_Update":"2020-09-15 03:30:30","Lat":40.3495,"Long_":-88.9861,"Confirmed":264831,"Deaths":8546,"Recovered":null,"Active":256285.0,"FIPS":17.0,"Incident_Rate":2089.920619933,"People_Tested":4773891.0,"Mortality_Rate":3.2269636108,"UID":84000017,"ISO3":"USA","Testing_Rate":37673.2831058772},{"Province_State":"Indiana","Country_Region":"US","Last_Update":"2020-09-15 03:30:30","Lat":39.8494,"Long_":-86.2583,"Confirmed":106540,"Deaths":3439,"Recovered":82311.0,"Active":20790.0,"FIPS":18.0,"Incident_Rate":1582.5391301145,"People_Tested":1247293.0,"Mortality_Rate":3.2278956261,"UID":84000018,"ISO3":"USA","Testing_Rate":18527.2196284761},{"Province_State":"Iowa","Country_Region":"US","Last_Update":"2020-09-15 03:30:30","Lat":42.0115,"Long_":-93.2105,"Confirmed":75064,"Deaths":1224,"Recovered":53417.0,"Active":20423.0,"FIPS":19.0,"Incident_Rate":2379.1548206537,"People_Tested":686636.0,"Mortality_Rate":1.6306085474,"UID":84000019,"ISO3":"USA","Testing_Rate":21762.9402834169},{"Province_State":"Kansas","Country_Region":"US","Last_Update":"2020-09-15 03:30:30","Lat":38.5266,"Long_":-96.7265,"Confirmed":49660,"Deaths":542,"Recovered":1887.0,"Active":47231.0,"FIPS":20.0,"Incident_Rate":1704.5879709499,"People_Tested":458381.0,"Mortality_Rate":1.0914216673,"UID":84000020,"ISO3":"USA","Testing_Rate":15734.0060151429},{"Province_State":"Kentucky","Country_Region":"US","Last_Update":"2020-09-15 03:30:30","Lat":37.6681,"Long_":-84.6701,"Confirmed":57282,"Deaths":1065,"Recovered":10918.0,"Active":45299.0,"FIPS":21.0,"Incident_Rate":1282.1439706979,"People_Tested":996575.0,"Mortality_Rate":1.8592227925,"UID":84000021,"ISO3":"USA","Testing_Rate":22306.3550085246},{"Province_State":"Louisiana","Country_Region":"US","Last_Update":"2020-09-15 03:30:30","Lat":31.1695,"Long_":-91.8678,"Confirmed":157947,"Deaths":5252,"Recovered":140440.0,"Active":12255.0,"FIPS":22.0,"Incident_Rate":3397.5908590486,"People_Tested":2079299.0,"Mortality_Rate":3.3251660367,"UID":84000022,"ISO3":"USA","Testing_Rate":44727.7078743433},{"Province_State":"Maine","Country_Region":"US","Last_Update":"2020-09-15 03:30:30","Lat":44.6939,"Long_":-69.3819,"Confirmed":4904,"Deaths":136,"Recovered":4237.0,"Active":531.0,"FIPS":23.0,"Incident_Rate":364.8234058318,"People_Tested":333777.0,"Mortality_Rate":2.7732463295,"UID":84000023,"ISO3":"USA","Testing_Rate":24830.6814698872},{"Province_State":"Maryland","Country_Region":"US","Last_Update":"2020-09-15 03:30:30","Lat":39.0639,"Long_":-76.8021,"Confirmed":116646,"Deaths":3839,"Recovered":7229.0,"Active":105578.0,"FIPS":24.0,"Incident_Rate":1929.410752802,"People_Tested":1464863.0,"Mortality_Rate":3.2911544331,"UID":84000024,"ISO3":"USA","Testing_Rate":24229.9129295629},{"Province_State":"Massachusetts","Country_Region":"US","Last_Update":"2020-09-15 03:30:30","Lat":42.2302,"Long_":-71.5301,"Confirmed":125080,"Deaths":9219,"Recovered":107501.0,"Active":8360.0,"FIPS":25.0,"Incident_Rate":1814.7253617445,"People_Tested":3038625.0,"Mortality_Rate":7.3704828909,"UID":84000025,"ISO3":"USA","Testing_Rate":44085.9438146055},{"Province_State":"Michigan","Country_Region":"US","Last_Update":"2020-09-15 03:30:30","Lat":43.3266,"Long_":-84.5361,"Confirmed":124287,"Deaths":6921,"Recovered":85513.0,"Active":31853.0,"FIPS":26.0,"Incident_Rate":1244.5056537808,"People_Tested":3162087.0,"Mortality_Rate":5.5685630838,"UID":84000026,"ISO3":"USA","Testing_Rate":31662.4840027248},{"Province_State":"Minnesota","Country_Region":"US","Last_Update":"2020-09-15 03:30:30","Lat":45.6945,"Long_":-93.9002,"Confirmed":84949,"Deaths":1974,"Recovered":78238.0,"Active":4737.0,"FIPS":27.0,"Incident_Rate":1506.2862257679,"People_Tested":1243355.0,"Mortality_Rate":2.3237471895,"UID":84000027,"ISO3":"USA","Testing_Rate":22046.7399291301},{"Province_State":"Mississippi","Country_Region":"US","Last_Update":"2020-09-15 03:30:30","Lat":32.7416,"Long_":-89.6787,"Confirmed":90018,"Deaths":2706,"Recovered":78971.0,"Active":8341.0,"FIPS":28.0,"Incident_Rate":3024.6469514799,"People_Tested":625806.0,"Mortality_Rate":3.0060654536,"UID":84000028,"ISO3":"USA","Testing_Rate":21027.374637493},{"Province_State":"Missouri","Country_Region":"US","Last_Update":"2020-09-15 03:30:30","Lat":38.4561,"Long_":-92.2884,"Confirmed":105278,"Deaths":1738,"Recovered":null,"Active":103540.0,"FIPS":29.0,"Incident_Rate":1715.3439518965,"People_Tested":1145207.0,"Mortality_Rate":1.6508672277,"UID":84000029,"ISO3":"USA","Testing_Rate":18659.3960857871},{"Province_State":"Montana","Country_Region":"US","Last_Update":"2020-09-15 03:30:30","Lat":46.9219,"Long_":-110.4544,"Confirmed":9107,"Deaths":138,"Recovered":6842.0,"Active":2127.0,"FIPS":30.0,"Incident_Rate":852.0946351815,"People_Tested":285870.0,"Mortality_Rate":1.5153178873,"UID":84000030,"ISO3":"USA","Testing_Rate":26747.3694256431},{"Province_State":"Nebraska","Country_Region":"US","Last_Update":"2020-09-15 03:30:30","Lat":41.1254,"Long_":-98.2681,"Confirmed":38642,"Deaths":435,"Recovered":29405.0,"Active":8802.0,"FIPS":31.0,"Incident_Rate":1997.6137402244,"People_Tested":403965.0,"Mortality_Rate":1.1257181305,"UID":84000031,"ISO3":"USA","Testing_Rate":20883.1332376624},{"Province_State":"Nevada","Country_Region":"US","Last_Update":"2020-09-15 03:30:30","Lat":38.3135,"Long_":-117.0554,"Confirmed":73814,"Deaths":1456,"Recovered":1938.0,"Active":70420.0,"FIPS":32.0,"Incident_Rate":2396.4370635773,"People_Tested":644871.0,"Mortality_Rate":1.9725255372,"UID":84000032,"ISO3":"USA","Testing_Rate":20936.3097193778},{"Province_State":"New Hampshire","Country_Region":"US","Last_Update":"2020-09-15 03:30:30","Lat":43.4525,"Long_":-71.5639,"Confirmed":7714,"Deaths":436,"Recovered":6987.0,"Active":291.0,"FIPS":33.0,"Incident_Rate":567.3264392213,"People_Tested":231816.0,"Mortality_Rate":5.6520611875,"UID":84000033,"ISO3":"USA","Testing_Rate":17048.9170125122},{"Province_State":"New Jersey","Country_Region":"US","Last_Update":"2020-09-15 03:30:30","Lat":40.2989,"Long_":-74.521,"Confirmed":196968,"Deaths":16034,"Recovered":34458.0,"Active":146476.0,"FIPS":34.0,"Incident_Rate":2217.5612095666,"People_Tested":3189970.0,"Mortality_Rate":8.1404085943,"UID":84000034,"ISO3":"USA","Testing_Rate":35914.2283603481},{"Province_State":"New Mexico","Country_Region":"US","Last_Update":"2020-09-15 03:30:30","Lat":34.8405,"Long_":-106.2485,"Confirmed":26842,"Deaths":823,"Recovered":14407.0,"Active":11612.0,"FIPS":35.0,"Incident_Rate":1280.123462619,"People_Tested":823145.0,"Mortality_Rate":3.0660904553,"UID":84000035,"ISO3":"USA","Testing_Rate":39256.6585067261},{"Province_State":"New York","Country_Region":"US","Last_Update":"2020-09-15 03:30:30","Lat":42.1657,"Long_":-74.9481,"Confirmed":444948,"Deaths":33030,"Recovered":75814.0,"Active":336104.0,"FIPS":36.0,"Incident_Rate":2287.2316281837,"People_Tested":9381651.0,"Mortality_Rate":7.4233393565,"UID":84000036,"ISO3":"USA","Testing_Rate":48225.8800843712},{"Province_State":"North Carolina","Country_Region":"US","Last_Update":"2020-09-15 03:30:30","Lat":35.6301,"Long_":-79.8064,"Confirmed":185780,"Deaths":3060,"Recovered":167257.0,"Active":15463.0,"FIPS":37.0,"Incident_Rate":1771.3435552194,"People_Tested":2634819.0,"Mortality_Rate":1.6471094843,"UID":84000037,"ISO3":"USA","Testing_Rate":25122.0241943142},{"Province_State":"North Dakota","Country_Region":"US","Last_Update":"2020-09-15 03:30:30","Lat":47.5289,"Long_":-99.784,"Confirmed":15831,"Deaths":170,"Recovered":12903.0,"Active":2758.0,"FIPS":38.0,"Incident_Rate":2077.3900286328,"People_Tested":527535.0,"Mortality_Rate":1.073842461,"UID":84000038,"ISO3":"USA","Testing_Rate":69224.6825061478},{"Province_State":"Northern Mariana Islands","Country_Region":"US","Last_Update":"2020-09-15 03:30:30","Lat":15.0979,"Long_":145.6739,"Confirmed":61,"Deaths":2,"Recovered":29.0,"Active":30.0,"FIPS":69.0,"Incident_Rate":110.6194690265,"People_Tested":14377.0,"Mortality_Rate":3.2786885246,"UID":580,"ISO3":"MNP","Testing_Rate":26071.7394458146},{"Province_State":"Ohio","Country_Region":"US","Last_Update":"2020-09-15 03:30:30","Lat":40.3888,"Long_":-82.7649,"Confirmed":138484,"Deaths":4419,"Recovered":115708.0,"Active":18357.0,"FIPS":39.0,"Incident_Rate":1184.7276522572,"People_Tested":2623256.0,"Mortality_Rate":3.1909823518,"UID":84000039,"ISO3":"USA","Testing_Rate":22441.8988630433},{"Province_State":"Oklahoma","Country_Region":"US","Last_Update":"2020-09-15 03:30:30","Lat":35.5653,"Long_":-96.9289,"Confirmed":70223,"Deaths":905,"Recovered":59007.0,"Active":10311.0,"FIPS":40.0,"Incident_Rate":1774.6655206723,"People_Tested":990399.0,"Mortality_Rate":1.2887515486,"UID":84000040,"ISO3":"USA","Testing_Rate":25029.2205831177},{"Province_State":"Oregon","Country_Region":"US","Last_Update":"2020-09-15 03:30:30","Lat":44.572,"Long_":-122.0709,"Confirmed":29337,"Deaths":509,"Recovered":5310.0,"Active":23518.0,"FIPS":41.0,"Incident_Rate":695.5625730101,"People_Tested":614804.0,"Mortality_Rate":1.7350103964,"UID":84000041,"ISO3":"USA","Testing_Rate":14576.6319711257},{"Province_State":"Pennsylvania","Country_Region":"US","Last_Update":"2020-09-15 03:30:30","Lat":40.5908,"Long_":-77.2098,"Confirmed":150000,"Deaths":7855,"Recovered":118951.0,"Active":23194.0,"FIPS":42.0,"Incident_Rate":1171.6929299033,"People_Tested":1829672.0,"Mortality_Rate":5.2366666667,"UID":84000042,"ISO3":"USA","Testing_Rate":14292.091642947},{"Province_State":"Puerto Rico","Country_Region":"US","Last_Update":"2020-09-15 03:30:30","Lat":18.2208,"Long_":-66.5901,"Confirmed":37750,"Deaths":542,"Recovered":null,"Active":37208.0,"FIPS":72.0,"Incident_Rate":1286.8990607512,"People_Tested":343722.0,"Mortality_Rate":1.4357615894,"UID":630,"ISO3":"PRI","Testing_Rate":11717.4971909806},{"Province_State":"Rhode Island","Country_Region":"US","Last_Update":"2020-09-15 03:30:30","Lat":41.6809,"Long_":-71.5118,"Confirmed":23130,"Deaths":1075,"Recovered":2223.0,"Active":19832.0,"FIPS":44.0,"Incident_Rate":2183.3916861202,"People_Tested":635718.0,"Mortality_Rate":4.6476437527,"UID":84000044,"ISO3":"USA","Testing_Rate":60009.5718079106},{"Province_State":"South Carolina","Country_Region":"US","Last_Update":"2020-09-15 03:30:30","Lat":33.8569,"Long_":-80.945,"Confirmed":132680,"Deaths":3077,"Recovered":51431.0,"Active":78172.0,"FIPS":45.0,"Incident_Rate":2576.9541675844,"People_Tested":1088473.0,"Mortality_Rate":2.3191136569,"UID":84000045,"ISO3":"USA","Testing_Rate":21140.6770700412},{"Province_State":"South Dakota","Country_Region":"US","Last_Update":"2020-09-15 03:30:30","Lat":44.2998,"Long_":-99.4388,"Confirmed":16801,"Deaths":184,"Recovered":14118.0,"Active":2499.0,"FIPS":46.0,"Incident_Rate":1899.1498419165,"People_Tested":165139.0,"Mortality_Rate":1.0951729064,"UID":84000046,"ISO3":"USA","Testing_Rate":18666.9665939079},{"Province_State":"Tennessee","Country_Region":"US","Last_Update":"2020-09-15 03:30:30","Lat":35.7478,"Long_":-86.6923,"Confirmed":174274,"Deaths":2097,"Recovered":156808.0,"Active":15369.0,"FIPS":47.0,"Incident_Rate":2551.9045202246,"People_Tested":2492851.0,"Mortality_Rate":1.2032775973,"UID":84000047,"ISO3":"USA","Testing_Rate":36502.965073082},{"Province_State":"Texas","Country_Region":"US","Last_Update":"2020-09-15 03:30:30","Lat":31.0545,"Long_":-97.5635,"Confirmed":685748,"Deaths":14451,"Recovered":577832.0,"Active":93465.0,"FIPS":48.0,"Incident_Rate":2364.9841851675,"People_Tested":5550139.0,"Mortality_Rate":2.1073338894,"UID":84000048,"ISO3":"USA","Testing_Rate":19141.1290451909},{"Province_State":"Utah","Country_Region":"US","Last_Update":"2020-09-15 03:30:30","Lat":40.15,"Long_":-111.8624,"Confirmed":58438,"Deaths":436,"Recovered":48934.0,"Active":9068.0,"FIPS":49.0,"Incident_Rate":1822.7936860059,"People_Tested":721682.0,"Mortality_Rate":0.746089873,"UID":84000049,"ISO3":"USA","Testing_Rate":22510.6504826327},{"Province_State":"Vermont","Country_Region":"US","Last_Update":"2020-09-15 03:30:30","Lat":44.0459,"Long_":-72.7107,"Confirmed":1696,"Deaths":58,"Recovered":1509.0,"Active":129.0,"FIPS":50.0,"Incident_Rate":271.7996631351,"People_Tested":151478.0,"Mortality_Rate":3.4198113208,"UID":84000050,"ISO3":"USA","Testing_Rate":24275.7484506938},{"Province_State":"Virgin Islands","Country_Region":"US","Last_Update":"2020-09-15 03:30:30","Lat":18.3358,"Long_":-64.8963,"Confirmed":1221,"Deaths":19,"Recovered":1144.0,"Active":58.0,"FIPS":78.0,"Incident_Rate":1138.2705000559,"People_Tested":18351.0,"Mortality_Rate":1.5561015561,"UID":850,"ISO3":"VIR","Testing_Rate":17107.6183018235},{"Province_State":"Virginia","Country_Region":"US","Last_Update":"2020-09-15 03:30:30","Lat":37.7693,"Long_":-78.17,"Confirmed":134493,"Deaths":2743,"Recovered":16361.0,"Active":115389.0,"FIPS":51.0,"Incident_Rate":1575.6862587969,"People_Tested":1779329.0,"Mortality_Rate":2.03951135,"UID":84000051,"ISO3":"USA","Testing_Rate":20846.1723300013},{"Province_State":"Washington","Country_Region":"US","Last_Update":"2020-09-15 03:30:30","Lat":47.4009,"Long_":-121.4905,"Confirmed":80138,"Deaths":2006,"Recovered":null,"Active":78132.0,"FIPS":53.0,"Incident_Rate":1052.3851090225,"People_Tested":1653967.0,"Mortality_Rate":2.503182011,"UID":84000053,"ISO3":"USA","Testing_Rate":21720.1607429021},{"Province_State":"West Virginia","Country_Region":"US","Last_Update":"2020-09-15 03:30:30","Lat":38.4912,"Long_":-80.9545,"Confirmed":12830,"Deaths":278,"Recovered":9361.0,"Active":3191.0,"FIPS":54.0,"Incident_Rate":715.9010951669,"People_Tested":488015.0,"Mortality_Rate":2.1667965705,"UID":84000054,"ISO3":"USA","Testing_Rate":27230.7461385701},{"Province_State":"Wisconsin","Country_Region":"US","Last_Update":"2020-09-15 03:30:30","Lat":44.2685,"Long_":-89.6165,"Confirmed":89956,"Deaths":1210,"Recovered":78527.0,"Active":10219.0,"FIPS":55.0,"Incident_Rate":1544.9896040041,"People_Tested":1369104.0,"Mortality_Rate":1.3451020499,"UID":84000055,"ISO3":"USA","Testing_Rate":23514.2897283164},{"Province_State":"Wyoming","Country_Region":"US","Last_Update":"2020-09-15 03:30:30","Lat":42.756,"Long_":-107.3025,"Confirmed":4394,"Deaths":42,"Recovered":3884.0,"Active":468.0,"FIPS":56.0,"Incident_Rate":759.2106559034,"People_Tested":89006.0,"Mortality_Rate":0.9558488848,"UID":84000056,"ISO3":"USA","Testing_Rate":15378.7673280243}]